LICENSE
README.md
setup.cfg
setup.py
src/cmarkwrapper/__init__.py
src/cmarkwrapper/func.py
src/cmarkwrapper/iter.py
src/cmarkwrapper/node.py
src/cmarkwrapper/parser.py
src/cmarkwrapper/types.py
src/cmarkwrapper.egg-info/PKG-INFO
src/cmarkwrapper.egg-info/SOURCES.txt
src/cmarkwrapper.egg-info/dependency_links.txt
src/cmarkwrapper.egg-info/requires.txt
src/cmarkwrapper.egg-info/top_level.txt